paywix/__init__.py
paywix/config.py
paywix/decorators.py
paywix/exceptions.py
paywix/gateway.py
paywix/payu.py
paywix-2.0.2.dist-info/AUTHORS.rst
paywix-2.0.2.dist-info/LICENSE
paywix-2.0.2.dist-info/METADATA
paywix-2.0.2.dist-info/WHEEL
paywix-2.0.2.dist-info/top_level.txt
paywix-2.0.2.dist-info/RECORD
