Metadata-Version: 2.1
Name: paywix
Version: 2.0.2
Summary: Paywix is a payment gateway wrapper is a application that integrates multiple payment gateways into a single platform. It simplifies the processing  payments by providing a unified API that allows merchants/Customer to access multiple payment gateways without having to write separate code for each gateway. This increases the ease of use and versatility for the merchants, and reduces the time and cost of development.
Home-page: https://github.com/renjithsraj/paywix
Download-URL: 
Author: Renjith S Raj
Author-email: renjithsraj@live.com
Maintainer: Renjith S Raj
Maintainer-email: renjithsraj@live.com
Keywords: payment gateway,payu,paytm,paywix,payment gateway wrapper,gateway
Classifier: Programming Language :: Python :: 3.8
Classifier: Programming Language :: Python :: 3 :: Only
Classifier: License :: OSI Approved :: MIT License
Classifier: Operating System :: OS Independent
Requires-Python: >=3.8
License-File: LICENSE
License-File: AUTHORS.rst
Requires-Dist: requests
